mcp_bill_track/__init__.py
mcp_bill_track/server.py
mcp_bill_track-0.2.0.dist-info/METADATA
mcp_bill_track-0.2.0.dist-info/WHEEL
mcp_bill_track-0.2.0.dist-info/entry_points.txt
mcp_bill_track-0.2.0.dist-info/top_level.txt
mcp_bill_track-0.2.0.dist-info/RECORD
