Metadata-Version: 2.4
Name: mcp_bill_track
Version: 0.2.0
Summary: 个人记账 MCP 服务
Keywords: bill,track,mcp
Requires-Python: >=3.12
Requires-Dist: mcp
